setup.py
Coins_Probability_Sauce/Bayes Practice.py
Coins_Probability_Sauce/Coins.py
Coins_Probability_Sauce/Coins_Load_Data.py
Coins_Probability_Sauce/__init__.py
Coins_Probability_Sauce/test.py
Coins_Probability_Sauce.egg-info/PKG-INFO
Coins_Probability_Sauce.egg-info/SOURCES.txt
Coins_Probability_Sauce.egg-info/dependency_links.txt
Coins_Probability_Sauce.egg-info/not-zip-safe
Coins_Probability_Sauce.egg-info/top_level.txt