Metadata-Version: 1.0
Name: Coins-Probability-Sauce
Version: 0.1
Summary: Probability of outcomes with a collection of coins
Home-page: UNKNOWN
Author: Billy Hansen
Author-email: billyhansen6@gmail.com
License: UNKNOWN
Platform: UNKNOWN
